cmdbrk/__init__.py
cmdbrk/cmdbrk.py
cmdbrk-0.0.4.dist-info/LICENSE
cmdbrk-0.0.4.dist-info/METADATA
cmdbrk-0.0.4.dist-info/WHEEL
cmdbrk-0.0.4.dist-info/top_level.txt
cmdbrk-0.0.4.dist-info/RECORD
