Metadata-Version: 2.1
Name: cmdbrk
Version: 0.0.4
Home-page: https://github.com/AregPrograms/cmdbrk.py
Author: Areg Harutyunyan
Author-email: harutyunyanareg2011@gmail.com
Classifier: Programming Language :: Python :: 3
Classifier: License :: OSI Approved :: MIT License
Classifier: Operating System :: OS Independent
Requires-Python: >=3.7
License-File: LICENSE
